{"id":"43847636","premium":false,"billing_type":{"id":"standard","name":"Стандарт"},"relations":[],"name":"Портфельный менеджер CRM кампаний","insider_interview":null,"response_letter_required":false,"area":{"id":"1","name":"Москва","url":"https://api.hh.ru/areas/1?host=hh.ru"},"salary":null,"type":{"id":"open","name":"Открытая"},"address":null,"allow_messages":true,"site":{"id":"hh","name":"hh.ru"},"experience":{"id":"between1And3","name":"От 1 года до 3 лет"},"schedule":{"id":"fullDay","name":"Полный день"},"employment":{"id":"full","name":"Полная занятость"},"department":null,"contacts":null,"description":"<p><strong>Обязанности:</strong></p> <ul> <li>Управление всем циклом конверсии первичных клиентов в кросс-продажи, включая меры по повышению конверсии в СRM-предложения и повышение конверсии из предложения в продажи;</li> <li>Управление портфелем кампаний для роста продаж кредитов наличными и кредитных карт (изменение плана кампаний, контактной политики и т.д);</li> <li>Подготовка требований для запуска пилотных CRM-кампаний;</li> <li>Документирование текущих CRM-кампаний;</li> <li>Анализ воронки на этапе формирования предложения: вхождение клиентов в сегмент, уровень одобрения в момент формирования предложения, % предложений от одобренных. Предложение мер по расширению воронки;</li> <li>Анализ воронки на коммуникации с клиентами, - соблюдение плана коммуникаций, обеспечение достаточности и полноты выгрузок в каналы коммуникаций. Предложение мер по расширению воронки;</li> <li>Подготовка отчетности об эффективности запущенных кампаний;</li> <li>Разработка правил подбора наиболее релевантного предложения;</li> <li>Разработка и согласование внутри Банка шаблонов коммуникаций.</li> </ul> <p><strong>Требования:</strong></p> <ul> <li>Высшее техническое или экономическое образование;</li> <li>Опыт работы в CRM, опыт подготовки и запуска целевых кампаний;</li> <li>Обязательно знание SQL.</li> </ul> <strong>Условия:</strong> <ul> <li>Работу в молодой и креативной команде профессионалов;</li> <li>Бесконечные возможности для повышения своего профессионального уровня (участие в инновационных проектах, различное внутренние и внешнее обучение и пр.);</li> <li>Достойный уровень заработной платы (оклад + премия + годовой бонус);</li> <li>Работу в комфортабельном офисе класса «А»;</li> <li>Многочисленные скидки и бонусы от партнеров.</li> </ul>","branded_description":null,"vacancy_constructor_template":null,"key_skills":[{"name":"SQL"},{"name":"Oracle Pl/SQL"},{"name":"Sas"},{"name":"CRM"}],"accept_handicapped":false,"accept_kids":false,"archived":false,"response_url":null,"specializations":[{"id":"5.27","name":"Аналитик","profarea_id":"5","profarea_name":"Банки, инвестиции, лизинг"},{"id":"1.536","name":"CRM системы","profarea_id":"1","profarea_name":"Информационные технологии, интернет, телеком"},{"id":"1.25","name":"Аналитик","profarea_id":"1","profarea_name":"Информационные технологии, интернет, телеком"},{"id":"3.26","name":"Аналитик","profarea_id":"3","profarea_name":"Маркетинг, реклама, PR"},{"id":"3.90","name":"Интернет-маркетинг","profarea_id":"3","profarea_name":"Маркетинг, реклама, PR"}],"code":null,"hidden":false,"quick_responses_allowed":false,"driver_license_types":[],"accept_incomplete_resumes":false,"employer":{"id":"1049556","name":"Почта Банк","url":"https://api.hh.ru/employers/1049556?host=hh.ru","alternate_url":"https://hh.ru/employer/1049556","logo_urls":{"240":"https://hhcdn.ru/employer-logo/1722907.jpeg","original":"https://hhcdn.ru/employer-logo-original/320135.jpg","90":"https://hhcdn.ru/employer-logo/1722906.jpeg"},"vacancies_url":"https://api.hh.ru/vacancies?employer_id=1049556&host=hh.ru","trusted":true},"published_at":"2021-05-17T12:56:40+0300","created_at":"2021-05-17T12:56:40+0300","negotiations_url":null,"suitable_resumes_url":null,"apply_alternate_url":"https://hh.ru/applicant/vacancy_response?vacancyId=43847636","has_test":false,"test":null,"alternate_url":"https://hh.ru/vacancy/43847636","working_days":[],"working_time_intervals":[],"working_time_modes":[],"accept_temporary":false}