{"id":"44725405","premium":false,"billing_type":{"id":"standard","name":"Стандарт"},"relations":[],"name":"Главный специалист Отдела разработки и внедрения кредитных стратегий","insider_interview":null,"response_letter_required":false,"area":{"id":"1","name":"Москва","url":"https://api.hh.ru/areas/1?host=hh.ru"},"salary":null,"type":{"id":"open","name":"Открытая"},"address":null,"allow_messages":true,"site":{"id":"hh","name":"hh.ru"},"experience":{"id":"between1And3","name":"От 1 года до 3 лет"},"schedule":{"id":"fullDay","name":"Полный день"},"employment":{"id":"full","name":"Полная занятость"},"department":null,"contacts":null,"description":"<strong>Обязанности:</strong> <ul> <li>Разработка функциональных требований в своей зоне ответственности;</li> <li>Разработка программ кредитных стратегий для ПО СПР Банка на основе функциональных требований;</li> <li>Подготовка планов тестирования СПР Банка в своей зоне ответственности;</li> <li>Проведение тестирования СПР Банка в своей зоне ответственности;</li> <li>Подготовка релиза СПР Банка и передача его поддержке на промышленные контура банка;</li> <li>Разработка процедур формирования показателей / агрегатов кредитных процедур в своей зоне ответственности в целях мониторинга;</li> <li>Проведение мероприятий и подготовка патчей, необходимых для устранения проблем ПО и сбоев кредитных процедур в своей зоне ответственности;</li> <li>Взаимодействие с другими подразделениями Банка по вопросам своей зоны ответственности.</li> </ul> <strong>Требования:</strong> <ul> <li>Высшее профессиональное образование;</li> <li> <p><strong>Опыт работы с большими массивами данных, хорошее знание </strong><strong>SQL;</strong></p> </li> <li>Приветствуются навыки программирования на платформе SAS: знание SAS Base, SAS Macro, знание форматов обмена данными (XML, json), опыт интеграции с внешними системами в синхронном и асинхронном режимах;</li> </ul> <strong>Условия:</strong> <ul> <li>Комфортабельный офис класса &quot;А&quot; сразу при выходе из ст. м.&quot;Преображенская площадь&quot;;</li> <li>Оформление согласно ТК РФ, соц.пакет, привлекательные программы ДМС (спустя год работы), бенефиты от партнеров;</li> <li>Система мотивации включает фикс.оклад + квартальные премии + годовой бонус. Финансовые условия обсуждаются на собеседовании с успешным кандидатом;</li> <li>Пятидневная рабочая неделя, выходные суббота и воскресенье.</li> </ul>","branded_description":null,"vacancy_constructor_template":null,"key_skills":[{"name":"SQL"},{"name":"XML"},{"name":"MS SQL"},{"name":"Анализ данных"},{"name":"Pascal"},{"name":"Sas"}],"accept_handicapped":false,"accept_kids":false,"archived":false,"response_url":null,"specializations":[{"id":"5.126","name":"Кредиты","profarea_id":"5","profarea_name":"Банки, инвестиции, лизинг"}],"code":null,"hidden":false,"quick_responses_allowed":false,"driver_license_types":[],"accept_incomplete_resumes":false,"employer":{"id":"1049556","name":"Почта Банк","url":"https://api.hh.ru/employers/1049556?host=hh.ru","alternate_url":"https://hh.ru/employer/1049556","logo_urls":{"240":"https://hhcdn.ru/employer-logo/1722907.jpeg","original":"https://hhcdn.ru/employer-logo-original/320135.jpg","90":"https://hhcdn.ru/employer-logo/1722906.jpeg"},"vacancies_url":"https://api.hh.ru/vacancies?employer_id=1049556&host=hh.ru","trusted":true},"published_at":"2021-05-19T17:53:17+0300","created_at":"2021-05-19T17:53:17+0300","negotiations_url":null,"suitable_resumes_url":null,"apply_alternate_url":"https://hh.ru/applicant/vacancy_response?vacancyId=44725405","has_test":false,"test":null,"alternate_url":"https://hh.ru/vacancy/44725405","working_days":[],"working_time_intervals":[],"working_time_modes":[],"accept_temporary":false}